honeybee/__init__.py
honeybee/__main__.py
honeybee/_base.py
honeybee/_basewithshade.py
honeybee/_lockable.py
honeybee/altnumber.py
honeybee/aperture.py
honeybee/boundarycondition.py
honeybee/checkdup.py
honeybee/colorobj.py
honeybee/config.json
honeybee/config.py
honeybee/dictutil.py
honeybee/door.py
honeybee/extensionutil.py
honeybee/face.py
honeybee/facetype.py
honeybee/logutil.py
honeybee/model.py
honeybee/orientation.py
honeybee/properties.py
honeybee/room.py
honeybee/search.py
honeybee/shade.py
honeybee/shademesh.py
honeybee/typing.py
honeybee/units.py
honeybee/cli/__init__.py
honeybee/cli/compare.py
honeybee/cli/create.py
honeybee/cli/edit.py
honeybee/cli/lib.py
honeybee/cli/setconfig.py
honeybee/cli/validate.py
honeybee/writer/__init__.py
honeybee/writer/aperture.py
honeybee/writer/door.py
honeybee/writer/face.py
honeybee/writer/model.py
honeybee/writer/room.py
honeybee/writer/shade.py
honeybee/writer/shademesh.py
honeybee_core-1.64.12.dist-info/licenses/LICENSE
honeybee_core-1.64.12.dist-info/METADATA
honeybee_core-1.64.12.dist-info/WHEEL
honeybee_core-1.64.12.dist-info/entry_points.txt
honeybee_core-1.64.12.dist-info/top_level.txt
honeybee_core-1.64.12.dist-info/RECORD
